{"cameraMode":{"drawMode":0,"name":"Shaded","section":"Shading Mode"},"sceneLighting":true,"audioPlay":false,"sceneViewState":{"m_AlwaysRefresh":false,"showFog":true,"showSkybox":false,"showFlares":true,"showImageEffects":true,"showParticleSystems":true,"showVisualEffectGraphs":true,"m_FxEnabled":true},"in2DMode":false,"pivot":{"x":5.837930679321289,"y":2.25,"z":118.29876708984375},"rotation":{"x":-0.04726065695285797,"y":0.6143761277198792,"z":0.03690524771809578,"w":0.7867292165756226},"size":8.161032676696778,"orthographic":false}